github_rate_limits_exporter/__init__.py
github_rate_limits_exporter/__main__.py
github_rate_limits_exporter/_version.py
github_rate_limits_exporter/cli.py
github_rate_limits_exporter/collector.py
github_rate_limits_exporter/constants.py
github_rate_limits_exporter/exceptions.py
github_rate_limits_exporter/github.py
github_rate_limits_exporter/utils.py
github_rate_limits_exporter-0.7.5.dist-info/LICENSE
github_rate_limits_exporter-0.7.5.dist-info/METADATA
github_rate_limits_exporter-0.7.5.dist-info/WHEEL
github_rate_limits_exporter-0.7.5.dist-info/entry_points.txt
github_rate_limits_exporter-0.7.5.dist-info/top_level.txt
github_rate_limits_exporter-0.7.5.dist-info/RECORD
