Metadata-Version: 2.1
Name: github_rate_limits_exporter
Version: 0.7.5
Summary: Prometheus exporter for Github rate-limits API
Home-page: https://github.com/theodore86/github-rate-limits-exporter
Author: Theodore Georgomanolis
Author-email: tgeorgomanolis@gmail.com
License: MIT
Platform: linux
Classifier: Development Status :: 5 - Production/Stable
Classifier: Intended Audience :: System Administrators
Classifier: Topic :: System :: Monitoring
Classifier: License :: OSI Approved :: MIT License
Classifier: Natural Language :: English
Classifier: Programming Language :: Python
Classifier: Programming Language :: Python :: 3
Classifier: Programming Language :: Python :: 3.8
Classifier: Programming Language :: Python :: 3.9
Classifier: Programming Language :: Python :: 3.10
Classifier: Programming Language :: Python :: 3.11
Classifier: Programming Language :: Python :: 3.12
Classifier: Topic :: Software Development :: Documentation
Requires-Python: >=3.8
License-File: LICENSE
Requires-Dist: cryptography==44.0.0
Requires-Dist: PyGithub==2.5.0
Requires-Dist: prometheus-client==0.21.1
Requires-Dist: dotmap==1.3.30
